[
  {
    "type": "text",
    "text": "```json\n[\n  {\n    \"title\": \"Ertrinkungsunfall - Hypothermie mit Reanimation\",\n    \"patient_age\": null,\n    \"patient_gender\": \"Mann\",\n    \"chief_complaints\": [\"Ertrinkungsunfall\", \"Unterkühlung\"],\n    \"accident_mechanism\": \"Im Winter aus dem See gezogen\",\n    \"pre_existing_conditions\": [],\n    \"medications\": [],\n    \"allergies\": [],\n    \"physical_examination\": [\"Unterkühlung\"],\n    \"imaging_findings\": [],\n    \"laboratory_findings\": [],\n    \"suspected_diagnosis\": [\"Hypothermie\", \"Ertrinkungsunfall\"],\n    \"diagnostic_approach\": [\"Reanimation bis Körpertemperatur mindestens 32°C erreicht\", \"Erwärmungsmaßnahmen im Krankenhaus\"]\n  },\n  {\n    \"title\": \"Schlaganfall - neuer neurologischer Ausfall\",\n    \"patient_age\": null,\n    \"patient_gender\": null,\n    \"chief_complaints\": [\"Neuer neurologischer Ausfall\"],\n    \"accident_mechanism\": null,\n    \"pre_existing_conditions\": [],\n    \"medications\": [],\n    \"allergies\": [],\n    \"physical_examination\": [\"Neurologischer Ausfall\"],\n    \"imaging_findings\": [\"CCT zur Blutungsausschluss\"],\n    \"laboratory_findings\": [],\n    \"suspected_diagnosis\": [\"Schlaganfall\", \"Ischämischer Schlaganfall\"],\n    \"diagnostic_approach\": [\"Sofortiges CCT\", \"Intravenöse Thrombolyse (Zeitfenster 4,5 Stunden)\", \"Interventionelle Thrombektomie (Zeitfenster bis 24 Stunden)\", \"Weiterbehandlung auf Stroke Unit\"]\n  }\n]\n```"
  }
]