[
  {
    "type": "text",
    "text": "```json\n[\n  {\n    \"title\": \"Knieschmerzen nach Umknicken beim Hundespaziergang\",\n    \"patient_age\": \"1968 geboren (ca. 55 Jahre alt zum Prüfungszeitpunkt)\",\n    \"patient_gender\": \"m\",\n    \"chief_complaints\": [\"Knieschmerzen\", \"Knie umgeknickt\"],\n    \"accident_mechanism\": \"Beim Spazierengehen im Wald mit Hund sei sein Knie umgeknickt. Der Hund war unruhig, hat gezogen, Knie verdreht, ist runtergefallen, mit dem Arm sich unterstützt in Extension, nicht auf dem Kopf\",\n    \"pre_existing_conditions\": [\n      \"Heuschnupfen\",\n      \"Hämorrhoiden\",\n      \"Asthma als Kind\",\n      \"Z.n. Cholezystektomie vor 11 Jahren\",\n      \"Atemnot vor 4 Wochen beim Jogging für ein paar Minuten (kein Brustschmerz)\"\n    ],\n    \"medications\": [\"Cetirizin\", \"Salbe für Hämorrhoiden\"],\n    \"allergies\": [],\n    \"physical_examination\": [\n      \"Vitalparameter durchgeführt\",\n      \"Rechtes Knie Inspektion\",\n      \"Knieuntersuchungen: Steinmann, Schublade, Lachmann, Payr\",\n      \"Steinmann I und II positiv\",\n      \"DMS rechtes Knie\",\n      \"Linke Seite und rechte Hand: DMS und grob Beweglichkeit unauffällig\",\n      \"Allgemeine KU: Kopf, Lymphknoten, Schilddrüse, Lunge, Herz, Abdomen\",\n      \"Suche nach peripheren Ödemen\",\n      \"Periphere Pulse\",\n      \"Reflexe\"\n    ],\n    \"imaging_findings\": [\n      \"Röntgen Knie rechts in 2 Ebenen: Patient kann Bein nicht heben (keine Extension), Patella luxiert, Quadriceps-Sehnen verletzt\",\n      \"MRT Knie: Mediales Seitenband Läsion, Läsion des vorderen Kreuzbands, Innenmeniskusriss\",\n      \"Röntgen Hand rechts: distale Radiusfraktur (Colles-Fraktur)\"\n    ],\n    \"laboratory_findings\": [],\n    \"suspected_diagnosis\": [\n      \"Patellaluxation\",\n      \"Quadriceps-Sehnenverletzung\",\n      \"Mediales Seitenbandläsion\",\n      \"Vordere Kreuzbandläsion\",\n      \"Innenmeniskusriss\",\n      \"Distale Radiusfraktur (Colles-Fraktur)\"\n    ],\n    \"diagnostic_approach\": [\n      \"Röntgen Knie rechts ggf. MRT\",\n      \"Röntgen Hand rechts\",\n      \"Röntgen Thorax\",\n      \"Lungenfunktionstest\",\n      \"Sonographie oder MRT zur besseren Beurteilung von Knieapparat-Verletzungen\",\n      \"Termin beim Lungenarzt zur weiteren Abklärung der Atemnot\"\n    ]\n  }\n]\n```"
  }
]