[
  {
    "type": "text",
    "text": "```json\n[\n  {\n    \"title\": \"Patellaluxation nach Sturz im Garten\",\n    \"patient_age\": null,\n    \"patient_gender\": \"w\",\n    \"chief_complaints\": [\"starke Knieschmerzen rechts\", \"Knieverdrehung\"],\n    \"accident_mechanism\": \"Ausrutschen beim Spielen mit Enkelkindern im Garten, dabei rechtes Knie verdreht\",\n    \"pre_existing_conditions\": [],\n    \"medications\": [],\n    \"allergies\": [],\n    \"physical_examination\": [\"Schmerzen verschwanden schlagartig nach Griff durch Sanitäter\"],\n    \"imaging_findings\": [\"Patella-Luxation nach lateral\"],\n    \"laboratory_findings\": [],\n    \"suspected_diagnosis\": [\"Patellaluxation nach lateral\"],\n    \"diagnostic_approach\": [\"Anamnese\", \"klinische Untersuchung\", \"Bildgebung\"]\n  },\n  {\n    \"title\": \"Knieverletzung mit Streckdefizit\",\n    \"patient_age\": null,\n    \"patient_gender\": null,\n    \"chief_complaints\": [\"konnte den Fuß gar nicht auf den Boden stellen\", \"Streckdefizit\"],\n    \"accident_mechanism\": null,\n    \"pre_existing_conditions\": [],\n    \"medications\": [],\n    \"allergies\": [],\n    \"physical_examination\": [\"Streckdefizit\", \"Fuß kann nicht auf Boden gestellt werden\"],\n    \"imaging_findings\": [\"Röntgen Knie: unauffällig außer Patella\", \"Patella Luxation\"],\n    \"laboratory_findings\": [],\n    \"suspected_diagnosis\": [\"VKB Ruptur\", \"Innenmeniskusverletzung\", \"Innenbandruptur\", \"Patellaluxation\"],\n    \"diagnostic_approach\": [\"Röntgen Knie\", \"klinische Untersuchung\"]\n  },\n  {\n    \"title\": \"Unhappy-Triad bei Verdrehtrauma im Kniegelenk\",\n    \"patient_age\": \"17-jähriger\",\n    \"patient_gender\": \"m\",\n    \"chief_complaints\": [\"starke Verdrehung im Kniegelenk\"],\n    \"accident_mechanism\": \"Verdrehtrauma im Kniegelenk beim Sport\",\n    \"pre_existing_conditions\": [],\n    \"medications\": [],\n    \"allergies\": [],\n    \"physical_examination\": [],\n    \"imaging_findings\": [\"axiale Schnitt mit Patella Fraktur\"],\n    \"laboratory_findings\": [],\n    \"suspected_diagnosis\": [\"Unhappy-Triad (ACL, Innenmeniskus, mediales Seitenband)\", \"Patellafraktur\"],\n    \"diagnostic_approach\": [\"klinische Untersuchung\", \"Bildgebung axial\"]\n  },\n  {\n    \"title\": \"Meniskusläsion mit positivem Steinzeichen\",\n    \"patient_age\": null,\n    \"patient_gender\": null,\n    \"chief_complaints\": [\"Steinzeichen positiv\"],\n    \"accident_mechanism\": null,\n    \"pre_existing_conditions\": [],\n    \"medications\": [],\n    \"allergies\": [],\n    \"physical_examination\": [\"Steinzeichen positiv\"],\n    \"imaging_findings\": [\"Röntgen Knie: unauffällig\", \"MRT T2: Seitenbandruptur\"],\n    \"laboratory_findings\": [],\n    \"suspected_diagnosis\": [\"Meniskusläsion\", \"Seitenbandruptur\"],\n    \"diagnostic_approach\": [\"klinische Untersuchung\", \"Röntgen Knie\", \"MRT T2\"]\n  }\n]\n```"
  }
]