[
  {
    "type": "text",
    "text": "```json\n[\n  {\n    \"title\": \"Akute Appendizitis mit Belastungsdyspnoe und Bursitis olecrani\",\n    \"patient_age\": null,\n    \"patient_gender\": null,\n    \"chief_complaints\": [\"Appendizitis\", \"Belastungsdyspnoe\"],\n    \"accident_mechanism\": null,\n    \"pre_existing_conditions\": [],\n    \"medications\": [],\n    \"allergies\": [],\n    \"physical_examination\": [\"Bursitis am Ellenbogen\"],\n    \"imaging_findings\": [\n      \"Sonografiebilder der Appendizitis\",\n      \"Laparoskopische Aufnahmen der Appendizitis\",\n      \"Olecranon-Fraktur\",\n      \"Lungenrundherd\",\n      \"Echo-Bilder (Klappenvitien)\",\n      \"CT-Abdomen\"\n    ],\n    \"laboratory_findings\": [],\n    \"suspected_diagnosis\": [\n      \"Akute Appendizitis\",\n      \"Belastungsdyspnoe\",\n      \"Bursitis olecrani\",\n      \"Mediastinitis\",\n      \"Chassaignac-Lähmung\",\n      \"Olecranon-Fraktur\",\n      \"Mitralinsuffizienz\",\n      \"Leberzirrhose\",\n      \"Aszitis\",\n      \"Hepatitis C\"\n    ],\n    \"diagnostic_approach\": [\n      \"Sonografie\",\n      \"Laparoskopie\",\n      \"Echokardiographie\"\n    ]\n  },\n  {\n    \"title\": \"PAVK mit Adynamie, Husten und Wadenschmerzen\",\n    \"patient_age\": \"69-jähriger\",\n    \"patient_gender\": \"m\",\n    \"chief_complaints\": [\"Adynamie\", \"Husten\", \"Schmerzen in der Wade\"],\n    \"accident_mechanism\": null,\n    \"pre_existing_conditions\": [\n      \"PAVK\",\n      \"Arterielle Hypertonie\",\n      \"Dyslipidämie\",\n      \"Zustand nach Spondylodese\",\n      \"Diabetes mellitus Typ 2\"\n    ],\n    \"medications\": [],\n    \"allergies\": [],\n    \"physical_examination\": [],\n    \"imaging_findings\": [\n      \"Röntgenbilder mit Tuberkulose\",\n      \"EKG\",\n      \"CT-Bild eines Aortenaneurysmas\",\n      \"CT-Bildbeschreibung\",\n      \"Grünholzfraktur des Radius\"\n    ],\n    \"laboratory_findings\": [],\n    \"suspected_diagnosis\": [\n      \"PAVK\",\n      \"Tuberkulose\",\n      \"Aortenaneurysma\",\n      \"Appendizitis\",\n      \"Pseudomembranöse Kolitis\",\n      \"Tibiafraktur (spiralförmig)\",\n      \"Subkapitale Fibulafraktur\",\n      \"Maisonneuve-Fraktur\",\n      \"Leriche-Syndrom\",\n      \"Embolie\",\n      \"Aneurysma der A. poplitea\",\n      \"HWI\",\n      \"Akute Dyspnoe\",\n      \"Krupp\",\n      \"Koma\"\n    ],\n    \"diagnostic_approach\": [\n      \"Röntgen\",\n      \"EKG\",\n      \"CT\",\n      \"Vigilanzbeurteilung\",\n      \"GCS\"\n    ]\n  }\n]\n```"
  }
]