[
  {
    "type": "text",
    "text": "```json\n[\n  {\n    \"title\": \"Riesenzellarteriitis mit Sehstörung\",\n    \"patient_age\": null,\n    \"patient_gender\": \"w\",\n    \"chief_complaints\": [\"verschwommenes Sehen seit heute Morgen\", \"Kopfschmerzen seit 2 Wochen\", \"Kraftminderungen\", \"nächtliches Schwitzen\"],\n    \"accident_mechanism\": null,\n    \"pre_existing_conditions\": [],\n    \"medications\": [],\n    \"allergies\": [],\n    \"physical_examination\": [\"Hautempfindlichkeit am Kopf\", \"Schmerzen beim Kauen\", \"Schluckbeschwerden\", \"Kernig negativ\", \"Brudzinski negativ\", \"Meningismus negativ\", \"kein Fieber\"],\n    \"imaging_findings\": [\"Dopplersonografie: Halozeichen\"],\n    \"laboratory_findings\": [\"BSG erhöht\"],\n    \"suspected_diagnosis\": [\"Riesenzellarteriitis\", \"Ausschluss Meningitis\", \"Ausschluss zentraler Arterienverschluss im Rahmen einer rheumatologischen Erkrankung\"],\n    \"diagnostic_approach\": [\"BSG\", \"Dopplersonografie\", \"RR beidseits messen\"]\n  },\n  {\n    \"title\": \"Lungenarterienembolie nach Flugreise\",\n    \"patient_age\": \"jung\",\n    \"patient_gender\": \"w\",\n    \"chief_complaints\": [\"Tachypnoe\"],\n    \"accident_mechanism\": null,\n    \"pre_existing_conditions\": [\"Adipositas\", \"Raucherin\"],\n    \"medications\": [],\n    \"allergies\": [],\n    \"physical_examination\": [],\n    \"imaging_findings\": [\"EKG: S1Q3, Rechtslagetyp, Rechtsherzbelastung\", \"QRS < 120 ms\"],\n    \"laboratory_findings\": [\"D-Dimere\"],\n    \"suspected_diagnosis\": [\"Lungenarterienembolie\"],\n    \"diagnostic_approach\": [\"Dopplersonografie der Beine\", \"D-Dimere\", \"EKG\", \"Score\", \"CT-Angio (vom Prüfer nicht gewünscht wegen Alter)\"]\n  },\n  {\n    \"title\": \"Gichtarthritis Großzehengrundgelenk\",\n    \"patient_age\": null,\n    \"patient_gender\": \"w\",\n    \"chief_complaints\": [],\n    \"accident_mechanism\": null,\n    \"pre_existing_conditions\": [],\n    \"medications\": [],\n    \"allergies\": [],\n    \"physical_examination\": [\"Grundgelenk deformiert\", \"gerötet\"],\n    \"imaging_findings\": [\"Röntgen: Gelenkspaltverschmälerung\", \"Gelenkdestruktion\", \"Erosionen des Knochens\", \"Osteolysen\", \"Tophus\"],\n    \"laboratory_findings\": [],\n    \"suspected_diagnosis\": [\"Gicht\"],\n    \"diagnostic_approach\": []\n  },\n  {\n    \"title\": \"Trimalleolarfraktur OSG\",\n    \"patient_age\": null,\n    \"patient_gender\": \"w\",\n    \"chief_complaints\": [],\n    \"accident_mechanism\": null,\n    \"pre_existing_conditions\": [],\n    \"medications\": [],\n    \"allergies\": [],\n    \"physical_examination\": [],\n    \"imaging_findings\": [\"Röntgen OSG: Trimalleolarfraktur\"],\n    \"laboratory_findings\": [],\n    \"suspected_diagnosis\": [\"Trimalleolarfraktur\"],\n    \"diagnostic_approach\": []\n  },\n  {\n    \"title\": \"Verdacht auf Kolorektalkarzinom\",\n    \"patient_age\": \"jung\",\n    \"patient_gender\": \"m\",\n    \"chief_complaints\": [],\n    \"accident_mechanism\": null,\n    \"pre_existing_conditions\": [],\n    \"medications\": [],\n    \"allergies\": [],\n    \"physical_examination\": [],\n    \"imaging_findings\": [\"Koloskopie: verdächtige Befunde\"],\n    \"laboratory_findings\": [],\n    \"suspected_diagnosis\": [\"Verdacht auf Kolorektalkarzinom\"],\n    \"diagnostic_approach\": [\"Koloskopie\"]\n  },\n  {\n    \"title\": \"Mononukleose\",\n    \"patient_age\": \"jung\",\n    \"patient_gender\": \"m\",\n    \"chief_complaints\": [\"Fieber seit ein paar Tagen\", \"AZ-Verschlechterung\", \"Halsschmerzen\"],\n    \"accident_mechanism\": null,\n    \"pre_existing_conditions\": [],\n    \"medications\": [],\n    \"allergies\": [],\n    \"physical_examination\": [\"weißer Belag an Tonsillen\", \"Lymphknotenvergrößerung überall\"],\n    \"imaging_findings\": [],\n    \"laboratory_findings\": [],\n    \"suspected_diagnosis\": [\"Mononukleose\"],\n    \"diagnostic_approach\": []\n  },\n  {\n    \"title\": \"Spannungspneumothorax mit Rippenfraktur\",\n    \"patient_age\": \"jung\",\n    \"patient_gender\": \"m\",\n    \"chief_complaints\": [],\n    \"accident_mechanism\": null,\n    \"pre_existing_conditions\": [],\n    \"medications\": [],\n    \"allergies\": [],\n    \"physical_examination\": [],\n    \"imaging_findings\": [\"Röntgen-Thorax: Spannungspneumothorax\", \"Rippe 2 Fraktur\", \"Hautemphysem\"],\n    \"laboratory_findings\": [],\n    \"suspected_diagnosis\": [\"Spannungspneumothorax\"],\n    \"diagnostic_approach\": []\n  },\n  {\n    \"title\": \"Temporalarteriitis mit Sehstörung (Fall 08.09. #1)\",\n    \"patient_age\": null,\n    \"patient_gender\": \"w\",\n    \"chief_complaints\": [\"Kopfschmerzen seit 2 Wochen\", \"Kieferschmerzen beim Essen\", \"Sehstörung seit heute Morgen\"],\n    \"accident_mechanism\": null,\n    \"pre_existing_conditions\": [\"Hypertonie\"],\n    \"medications\": [],\n    \"allergies\": [],\n    \"physical_examination\": [\"Fieber fraglich\"],\n    \"imaging_findings\": [\"CT Bild mit Arteritis\"],\n    \"laboratory_findings\": [],\n    \"suspected_diagnosis\": [\"Temporal arteritis\", \"initial VD: Migräne\", \"DD: Meningitis\"],\n    \"diagnostic_approach\": [\"Labor\", \"LP (falls Meningitis positiv)\", \"CT\"]\n  }\n]\n```"
  }
]